esp_idf_docs_mcp/__init__.py
esp_idf_docs_mcp/config.py
esp_idf_docs_mcp/exceptions.py
esp_idf_docs_mcp/explorer.py
esp_idf_docs_mcp/server.py
esp_idf_docs_mcp/util.py
esp_idf_docs_mcp/web_explorer.py
esp_idf_docs_mcp-0.1.5.dist-info/METADATA
esp_idf_docs_mcp-0.1.5.dist-info/WHEEL
esp_idf_docs_mcp-0.1.5.dist-info/entry_points.txt
esp_idf_docs_mcp-0.1.5.dist-info/licenses/LICENSE
esp_idf_docs_mcp-0.1.5.dist-info/RECORD
