Metadata-Version: 2.4
Name: esp-idf-docs-mcp
Version: 0.1.5
Summary: ESP-IDF Documentation Explorer MCP Server
Project-URL: Homepage, https://github.com/raihalea/esp-idf-docs
Project-URL: Repository, https://github.com/raihalea/esp-idf-docs.git
Project-URL: Issues, https://github.com/raihalea/esp-idf-docs/issues
Author-email: raihalea <raihalea@users.noreply.github.com>
License: 
License-File: LICENSE
Keywords: documentation,esp-idf,mcp,server
Classifier: Development Status :: 4 - Beta
Classifier: Intended Audience :: Developers
Classifier: License :: OSI Approved :: MIT License
Classifier: Programming Language :: Python :: 3
Classifier: Programming Language :: Python :: 3.12
Classifier: Topic :: Internet :: WWW/HTTP :: Indexing/Search
Classifier: Topic :: Software Development :: Documentation
Requires-Python: >=3.12
Requires-Dist: beautifulsoup4>=4.13.0
Requires-Dist: fastmcp>=0.5.0
Requires-Dist: httpx>=0.25.0
Requires-Dist: lxml>=6.0.0
